lifeblood_viewer/__init__.py
lifeblood_viewer/breeze_resources.py
lifeblood_viewer/connection_worker.py
lifeblood_viewer/db_misc.py
lifeblood_viewer/editor_scene_integration.py
lifeblood_viewer/fancy_scene_item_factory.py
lifeblood_viewer/graphics_scene.py
lifeblood_viewer/graphics_scene_viewing_widget.py
lifeblood_viewer/graphics_scene_with_data_controller.py
lifeblood_viewer/imgui_opengl_hotfix.py
lifeblood_viewer/launch.py
lifeblood_viewer/lifeblood_viewer.py
lifeblood_viewer/long_op.py
lifeblood_viewer/menu_entry_base.py
lifeblood_viewer/nodeeditor.py
lifeblood_viewer/save_node_settings_dialog.py
lifeblood_viewer/scene_data_controller.py
lifeblood_viewer/scene_item_factory_base.py
lifeblood_viewer/scene_ops.py
lifeblood_viewer/task_group_actions.py
lifeblood_viewer/ui_elements_base.py
lifeblood_viewer/ui_scene_elements.py
lifeblood_viewer/ui_snippets.py
lifeblood_viewer/undo_stack.py
lifeblood_viewer/utils.py
lifeblood_viewer/code_editor/__init__.py
lifeblood_viewer/code_editor/editor.py
lifeblood_viewer/graphics_items/__init__.py
lifeblood_viewer/graphics_items/graphics_items.py
lifeblood_viewer/graphics_items/graphics_scene_base.py
lifeblood_viewer/graphics_items/graphics_scene_container.py
lifeblood_viewer/graphics_items/network_item.py
lifeblood_viewer/graphics_items/network_item_watchers.py
lifeblood_viewer/graphics_items/qextended_graphics_item.py
lifeblood_viewer/graphics_items/scene_network_item.py
lifeblood_viewer/graphics_items/utils.py
lifeblood_viewer/graphics_items/pretty_items/__init__.py
lifeblood_viewer/graphics_items/pretty_items/decorated_node.py
lifeblood_viewer/graphics_items/pretty_items/drawable_node.py
lifeblood_viewer/graphics_items/pretty_items/drawable_node_with_snap_points.py
lifeblood_viewer/graphics_items/pretty_items/drawable_task.py
lifeblood_viewer/graphics_items/pretty_items/node_connection_create_preview.py
lifeblood_viewer/graphics_items/pretty_items/node_connection_snap_point.py
lifeblood_viewer-0.13.0.dist-info/METADATA
lifeblood_viewer-0.13.0.dist-info/WHEEL
lifeblood_viewer-0.13.0.dist-info/entry_points.txt
lifeblood_viewer-0.13.0.dist-info/top_level.txt
lifeblood_viewer-0.13.0.dist-info/RECORD
