Metadata-Version: 2.4
Name: lifeblood-viewer
Version: 0.13.0
Summary: view the LIFEBLOOD !!
Home-page: https://github.com/pedohorse/lifeblood
Author: XAPKOHHEH
Project-URL: Bug Tracker, https://github.com/pedohorse/lifeblood/issues
Classifier: Programming Language :: Python :: 3
Classifier: License :: OSI Approved :: GNU General Public License v3 or later (GPLv3+)
Classifier: Operating System :: OS Independent
Requires-Python: <3.12,>=3.9
Requires-Dist: imgui~=2.0
Requires-Dist: glfw~=2.5
Requires-Dist: PyOpenGL~=3.1
Requires-Dist: PySide6<6.10,>=6.8
Requires-Dist: lz4~=4.0
Requires-Dist: lifeblood~=0.1
Requires-Dist: grandalf~=0.7
Requires-Dist: numpy~=1.21
